_common/__init__.py
_common/metrics.py
_common/qcb_mpi.py
_common/qedc_init.py
_common/braket/__init__.py
_common/braket/execute.py
_common/cirq/__init__.py
_common/cirq/cirq_utils.py
_common/cirq/execute.py
_common/cudaq/__init__.py
_common/cudaq/execute.py
_common/custom/__init__.py
_common/custom/custom_qiskit_noise_model.py
_common/executors/__init__.py
_common/executors/bluequbit_executor.py
_common/executors/cuquantum_executor.py
_common/executors/fire_opal_executor.py
_common/ocean/HamiltonianCircuitProxy.py
_common/ocean/__init__.py
_common/ocean/execute.py
_common/postprocessors/__init__.py
_common/postprocessors/mthree/__init__.py
_common/postprocessors/mthree/mthree_em.py
_common/qiskit/__init__.py
_common/qiskit/benchmark_runner.py
_common/qiskit/execute.py
_common/transformers/__init__.py
_common/transformers/qiskit_passmgr.py
_common/transformers/tket_optimiser.py
_common/transformers/trueq_rc.py
bernstein_vazirani/__init__.py
bernstein_vazirani/bv_benchmark.py
bernstein_vazirani/braket/__init__.py
bernstein_vazirani/braket/bv_benchmark.py
bernstein_vazirani/cirq/__init__.py
bernstein_vazirani/cirq/bv_benchmark.py
bernstein_vazirani/cudaq/__init__.py
bernstein_vazirani/cudaq/bv_kernel.py
bernstein_vazirani/qiskit/__init__.py
bernstein_vazirani/qiskit/bv_benchmark.py
bernstein_vazirani/qiskit/bv_kernel.py
hidden_shift/__init__.py
hidden_shift/hs_benchmark.py
hidden_shift/braket/__init__.py
hidden_shift/braket/hs_benchmark.py
hidden_shift/cirq/__init__.py
hidden_shift/cirq/hs_benchmark.py
hidden_shift/cudaq/__init__.py
hidden_shift/cudaq/hs_kernel.py
hidden_shift/qiskit/__init__.py
hidden_shift/qiskit/hs_benchmark.py
hidden_shift/qiskit/hs_kernel.py
metriq_gym/__init__.py
metriq_gym/_version.py
metriq_gym/circuits.py
metriq_gym/cli.py
metriq_gym/constants.py
metriq_gym/exceptions.py
metriq_gym/job_manager.py
metriq_gym/paths.py
metriq_gym/registry.py
metriq_gym/resource_estimation.py
metriq_gym/run.py
metriq_gym/schema_validator.py
metriq_gym-0.6.1.dist-info/licenses/LICENSE
metriq_gym-0.6.1.dist-info/licenses/submodules/QC-App-Oriented-Benchmarks/LICENSE
metriq_gym-0.6.1.dist-info/licenses/submodules/qiskit-device-benchmarking/LICENSE
metriq_gym-0.6.1.dist-info/METADATA
metriq_gym-0.6.1.dist-info/WHEEL
metriq_gym-0.6.1.dist-info/entry_points.txt
metriq_gym-0.6.1.dist-info/top_level.txt
metriq_gym-0.6.1.dist-info/RECORD
