Metadata-Version: 2.4
Name: metriq-gym
Version: 0.6.1
Summary: Framework for implementing and running standard quantum benchmarks on different quantum devices by different providers.
Author-email: Unitary Foundation team <metriq@unitary.foundation>
Maintainer-email: Alessandro Cosentino <alessandro@unitary.foundation>, Vincent Russo <vincent@unitary.foundation>
License-Expression: Apache-2.0
Classifier: Development Status :: 3 - Alpha
Classifier: Intended Audience :: Science/Research
Classifier: Topic :: Scientific/Engineering :: Quantum Computing
Classifier: Topic :: System :: Benchmark
Classifier: Operating System :: MacOS :: MacOS X
Classifier: Operating System :: Microsoft :: Windows
Classifier: Operating System :: POSIX :: Linux
Classifier: Programming Language :: Python :: 3
Classifier: Programming Language :: Python :: 3.12
Classifier: Programming Language :: Python :: 3.13
Requires-Python: <3.14,>=3.12
License-File: LICENSE
License-File: submodules/qiskit-device-benchmarking/LICENSE
License-File: submodules/QC-App-Oriented-Benchmarks/LICENSE
Requires-Dist: jsonschema<5.0.0,>=4.25.1
Requires-Dist: pyqrack<2.0.0,>=1.69.0
Requires-Dist: python-dotenv<2.0.0,>=1.0.1
Requires-Dist: pydantic<2.13,>=2.5.0
Requires-Dist: qiskit<3.0,>=1.4.3
Requires-Dist: qiskit-experiments<0.14.0,>=0.9.0
Requires-Dist: qiskit-aer<0.18.0,>=0.17.1
Requires-Dist: qiskit-ibm-runtime<0.46.0,>=0.41.1
Requires-Dist: scipy<2.0.0,>=1.16.2
Requires-Dist: tabulate<0.10.0,>=0.9.0
Requires-Dist: typer<1.0.0,>=0.21.1
Requires-Dist: qbraid[azure,braket,cirq,ionq,qiskit]<0.10.2,>=0.10.0
Requires-Dist: ruamel-yaml-clib==0.2.15; sys_platform == "darwin" and platform_machine == "arm64"
Requires-Dist: ruamel-yaml-clib==0.2.15; sys_platform == "darwin" and platform_machine == "x86_64"
Requires-Dist: myst-nb<2.0.0,>=1.3.0
Requires-Dist: platformdirs<5.0.0,>=4.4.0
Requires-Dist: dimod<0.13.0,>=0.12.20
Requires-Dist: qnexus<1.0.0,>=0.39.0
Requires-Dist: pytket-qiskit<0.77.0,>=0.71.0
Requires-Dist: pyqpanda3>=0.3.2
Provides-Extra: docs
Requires-Dist: mkdocs>=1.5; extra == "docs"
Requires-Dist: mkdocs-material>=9.0; extra == "docs"
Requires-Dist: mkdocstrings[python]>=0.24; extra == "docs"
Dynamic: license-file
